AUDUSD/__init__.py
AUDUSD/audusd.py
AUDUSD_xiaxin-0.1.1.dist-info/METADATA
AUDUSD_xiaxin-0.1.1.dist-info/WHEEL
AUDUSD_xiaxin-0.1.1.dist-info/top_level.txt
AUDUSD_xiaxin-0.1.1.dist-info/RECORD
